{
  "appPageId" : "befed4fd-2f6f-4557-839c-e5cc4de89a29",
  "componentName" : "siteforce:sldsOneColLayout",
  "dataProviders" : [ ],
  "id" : "0f9e157a-7ff9-4f87-a5aa-91e0b2a006d2",
  "label" : "Account Related List",
  "regions" : [ {
    "id" : "19ee7be2-ed7f-4622-a28e-d1697938d927",
    "regionName" : "header",
    "type" : "region"
  }, {
    "components" : [ {
      "componentAttributes" : {
        "customTitle" : "",
        "parentRecordId" : "{!recordId}",
        "relatedListName" : "{!relationshipApiName}",
        "showBreadCrumbs" : true,
        "showCustomTitle" : false,
        "showManualRefreshButton" : true,
        "showRowNumbers" : true
      },
      "componentName" : "forceCommunity:relatedList",
      "id" : "4be2e750-5f5f-48fe-aa68-4b2ea691bf2e",
      "renderPriority" : "NEUTRAL",
      "renditionMap" : { },
      "type" : "component"
    } ],
    "id" : "152778a5-f996-4ef9-a209-aa7e4480a137",
    "regionName" : "content",
    "type" : "region"
  }, {
    "id" : "5a3dc462-3e48-431d-94f0-928adab6e883",
    "regionName" : "footer",
    "type" : "region"
  } ],
  "themeLayoutType" : "Inner",
  "type" : "view",
  "viewType" : "relatedlist-001"
}